azure/mgmt/common/arm.py
azure/mgmt/common/filters.py
azure/mgmt/common/__init__.py
azure_mgmt_common-0.20.0rc2.dist-info/DESCRIPTION.rst
azure_mgmt_common-0.20.0rc2.dist-info/METADATA
azure_mgmt_common-0.20.0rc2.dist-info/metadata.json
azure_mgmt_common-0.20.0rc2.dist-info/RECORD
azure_mgmt_common-0.20.0rc2.dist-info/top_level.txt
azure_mgmt_common-0.20.0rc2.dist-info/WHEEL
