Metadata-Version: 2.0
Name: azure-mgmt-common
Version: 0.20.0rc2
Summary: Microsoft Azure Resource Management Client Library for Python (Common)
Home-page: https://github.com/Azure/azure-sdk-for-python
Author: Microsoft Corporation
Author-email: ptvshelp@microsoft.com
License: Apache License 2.0
Platform: UNKNOWN
Classifier: Development Status :: 4 - Beta
Classifier: Programming Language :: Python
Classifier: Programming Language :: Python :: 2
Classifier: Programming Language :: Python :: 2.7
Classifier: Programming Language :: Python :: 3
Classifier: Programming Language :: Python :: 3.3
Classifier: Programming Language :: Python :: 3.4
Classifier: License :: OSI Approved :: Apache Software License
Requires-Dist: azure-common
Requires-Dist: azure-mgmt-nspkg
